airflow/providers/cncf/kubernetes/__init__.py
airflow/providers/cncf/kubernetes/callbacks.py
airflow/providers/cncf/kubernetes/exceptions.py
airflow/providers/cncf/kubernetes/get_provider_info.py
airflow/providers/cncf/kubernetes/k8s_model.py
airflow/providers/cncf/kubernetes/kube_client.py
airflow/providers/cncf/kubernetes/kube_config.py
airflow/providers/cncf/kubernetes/kubernetes_helper_functions.py
airflow/providers/cncf/kubernetes/pod_generator.py
airflow/providers/cncf/kubernetes/python_kubernetes_script.jinja2
airflow/providers/cncf/kubernetes/python_kubernetes_script.py
airflow/providers/cncf/kubernetes/secret.py
airflow/providers/cncf/kubernetes/template_rendering.py
airflow/providers/cncf/kubernetes/version_compat.py
airflow/providers/cncf/kubernetes/backcompat/__init__.py
airflow/providers/cncf/kubernetes/backcompat/backwards_compat_converters.py
airflow/providers/cncf/kubernetes/cli/__init__.py
airflow/providers/cncf/kubernetes/cli/kubernetes_command.py
airflow/providers/cncf/kubernetes/decorators/__init__.py
airflow/providers/cncf/kubernetes/decorators/kubernetes.py
airflow/providers/cncf/kubernetes/decorators/kubernetes_cmd.py
airflow/providers/cncf/kubernetes/executors/__init__.py
airflow/providers/cncf/kubernetes/executors/kubernetes_executor.py
airflow/providers/cncf/kubernetes/executors/kubernetes_executor_types.py
airflow/providers/cncf/kubernetes/executors/kubernetes_executor_utils.py
airflow/providers/cncf/kubernetes/executors/local_kubernetes_executor.py
airflow/providers/cncf/kubernetes/hooks/__init__.py
airflow/providers/cncf/kubernetes/hooks/kubernetes.py
airflow/providers/cncf/kubernetes/kubernetes_executor_templates/__init__.py
airflow/providers/cncf/kubernetes/kubernetes_executor_templates/basic_template.yaml
airflow/providers/cncf/kubernetes/operators/__init__.py
airflow/providers/cncf/kubernetes/operators/custom_object_launcher.py
airflow/providers/cncf/kubernetes/operators/job.py
airflow/providers/cncf/kubernetes/operators/kueue.py
apache_airflow_providers_cncf_kubernetes-10.11.1.dist-info/entry_points.txt
apache_airflow_providers_cncf_kubernetes-10.11.1.dist-info/licenses/LICENSE
apache_airflow_providers_cncf_kubernetes-10.11.1.dist-info/licenses/NOTICE
apache_airflow_providers_cncf_kubernetes-10.11.1.dist-info/WHEEL
apache_airflow_providers_cncf_kubernetes-10.11.1.dist-info/METADATA
apache_airflow_providers_cncf_kubernetes-10.11.1.dist-info/RECORD
